echoflow/__init__.py
echoflow/echoflow.py
echoflow/transformer.py
echoflow/core/__init__.py
echoflow/core/base.py
echoflow/core/batch_norm.py
echoflow/core/coupling.py
echoflow/core/made.py
echoflow/core/one_hot.py
echoflow/core/reverse.py
echoflow/core/sequential.py
echoflow/demo/__init__.py
echoflow-0.0.2.dist-info/LICENSE
echoflow-0.0.2.dist-info/METADATA
echoflow-0.0.2.dist-info/WHEEL
echoflow-0.0.2.dist-info/top_level.txt
echoflow-0.0.2.dist-info/RECORD
